{
    "items": [
        {
            "type": "header",
            "navigation": 
                {
                    "name": "Nicolás Escobar Valle",
                    "year": 2019
                }
        },
        {
            "type": "hamburger",
            "menuLabel" : "menú"
        },
        {
            "type": "hero",
            "scrollLabel": "scroll",
            "helloLabel": "Hello",
            "nameLabel" : "I'm Nico",
            "meetLabel": "Nice to meet you"
        },
        {
            "type": "footer",
            "social": [
                {
                    "name": "twitter",
                    "icon": "",
                    "alt": "Twitter",
                    "url": "http://twitter.com/_burningsoul9"
                },
                {
                    "name": "instagram",
                    "icon": "",
                    "alt": "Instagram",
                    "url": "http://instagram.com/iamnikiyo"
                },
                {
                    "name": "linkedin",
                    "icon": "",
                    "alt": "LinkedIn",
                    "url": "https://linkedin.com/in/nicolas-escobar-valle"
                }
            ]
        }
    ]
}